[
    {
        "page": "new-article",
        "url": "/new/"
    },
    {
        "page": "settings",
        "url": "/settings/"
    },
    {
        "page": "home",
        "url": "/"
    },
    {
        "page": "user",
        "url": "/profile/"
    },
    {
        "page": "contact-us",
        "url": "/contact/"
    },
    {
        "page": "signout",
        "url": "/"
    },
    {
        "page": "signin",
        "url": "/login/"
    },
    {
        "page": "signup",
        "url": "/register/"
    }
]
